[{"username":"Geroge","item":"Carrots","funcs":"2","price":"100","description":"Very delicious"},{"username":"Nhi","item":"Cup set","funcs":"2","price":"100","description":"Nice cups"},{"username":"Giang","item":"Tea","funcs":"1","price":"10","description":"Great tea"},{"username":"Lily","item":"French Book","funcs":"2","price":"100","categories":"5","description":"Great French book. New","greenDescription":"Save forest!","co2":"100mg","greenCert":"environment","image":"svn1 (1).png"},{"username":"Lily","item":"books","funcs":"1","price":"100","categories":"5","description":"Great bookkkkks","greenDescription":"Save the environment","co2":"1000mg","greenCert":"water","image":"aa.PNG"},{"username":"Username","item":"Item name","funcs":"3","price":"1000","categories":"3","description":"Great","greenDescription":"Great","co2":"1000mg","greenCert":"energyStar","image":"154.jpg"},{"username":"Username","item":"Item name","funcs":"2","price":"100","categories":"1","description":"fwfdas","greenDescription":"sdfsa","co2":"fsdaf","greenCert":"energyStar","image":"154.jpg"},{"username":"Username","item":"Item name","funcs":"1","price":"100","categories":"1","description":"SASVCAS","greenDescription":"cscsd","co2":"cscs","greenCert":"energyStar","image":"154.jpg"},{"username":"Username","item":"Item name","funcs":"2","price":"100","categories":"1","description":"casc","greenDescription":"csacsa","co2":"cacasa","greenCert":"energyStar","image":"154.jpg"},{"username":"Username","item":"Item name","funcs":"2","price":"100","categories":"1","description":"faefadsfdsfdas","greenDescription":"vsaddsavas","co2":"vdsasdva","greenCert":"energyStar","image":"154.jpg"}]
